sleep_even/__init__.py
sleep_even/py.typed
sleep_even-0.1.0.dist-info/LICENSE
sleep_even-0.1.0.dist-info/METADATA
sleep_even-0.1.0.dist-info/WHEEL
sleep_even-0.1.0.dist-info/RECORD
