Metadata-Version: 2.3
Name: sleep-even
Version: 0.1.0
Summary: Is even?
License: MIT
Author: Micael Jarniac
Author-email: micael@jarniac.dev
Requires-Python: >=3.9,<4.0
Classifier: Development Status :: 1 - Planning
Classifier: License :: OSI Approved :: MIT License
Classifier: Natural Language :: English
Classifier: Operating System :: OS Independent
Classifier: Programming Language :: Python :: 3
Classifier: Programming Language :: Python :: 3.9
Classifier: Programming Language :: Python :: 3.10
Classifier: Programming Language :: Python :: 3.11
Classifier: Programming Language :: Python :: 3.12
Classifier: Programming Language :: Python :: 3.13
Classifier: Typing :: Typed
Project-URL: Bug Tracker, https://github.com/MicaelJarniac/sleep-even/issues
Project-URL: Changelog, https://github.com/MicaelJarniac/sleep-even/blob/main/docs/CHANGELOG.md
Project-URL: Documentation, https://sleep-even.readthedocs.io
Project-URL: Homepage, https://github.com/MicaelJarniac/sleep-even
Project-URL: Repository, https://github.com/MicaelJarniac/sleep-even
